ScriptCollection/AnionBuildPlatform.py
ScriptCollection/CertificateUpdater.py
ScriptCollection/Executables.py
ScriptCollection/GeneralUtilities.py
ScriptCollection/ImageUpdater.py
ScriptCollection/ProcessesRunner.py
ScriptCollection/ProgramRunnerBase.py
ScriptCollection/ProgramRunnerMock.py
ScriptCollection/ProgramRunnerPopen.py
ScriptCollection/ProgramRunnerSudo.py
ScriptCollection/SCLog.py
ScriptCollection/ScriptCollectionCore.py
ScriptCollection/__init__.py
ScriptCollection/OCIImages/AbstractImageHandler.py
ScriptCollection/OCIImages/OCIImageManager.py
ScriptCollection/OCIImages/__init__.py
ScriptCollection/OCIImages/ConcreteImageHandlers/ImageHandlerDebian.py
ScriptCollection/OCIImages/ConcreteImageHandlers/ImageHandlerDebianSlim.py
ScriptCollection/OCIImages/ConcreteImageHandlers/ImageHandlerGeneric.py
ScriptCollection/OCIImages/ConcreteImageHandlers/ImageHandlerGenericV.py
ScriptCollection/OCIImages/ConcreteImageHandlers/__init__.py
ScriptCollection/TFCPS/TFCPS_CodeUnitSpecific_Base.py
ScriptCollection/TFCPS/TFCPS_CodeUnit_BuildCodeUnit.py
ScriptCollection/TFCPS/TFCPS_CodeUnit_BuildCodeUnits.py
ScriptCollection/TFCPS/TFCPS_CreateRelease.py
ScriptCollection/TFCPS/TFCPS_Generic.py
ScriptCollection/TFCPS/TFCPS_MergeToMain.py
ScriptCollection/TFCPS/TFCPS_MergeToStable.py
ScriptCollection/TFCPS/TFCPS_PreBuildCodeunitsScript.py
ScriptCollection/TFCPS/TFCPS_Tools_General.py
ScriptCollection/TFCPS/__init__.py
ScriptCollection/TFCPS/Docker/TFCPS_CodeUnitSpecific_Docker.py
ScriptCollection/TFCPS/Docker/__init__.py
ScriptCollection/TFCPS/DotNet/CertificateGeneratorInformationBase.py
ScriptCollection/TFCPS/DotNet/CertificateGeneratorInformationGenerate.py
ScriptCollection/TFCPS/DotNet/CertificateGeneratorInformationNoGenerate.py
ScriptCollection/TFCPS/DotNet/TFCPS_CodeUnitSpecific_DotNet.py
ScriptCollection/TFCPS/DotNet/__init__.py
ScriptCollection/TFCPS/Flutter/TFCPS_CodeUnitSpecific_Flutter.py
ScriptCollection/TFCPS/Flutter/__init__.py
scriptcollection-4.2.35.dist-info/METADATA
scriptcollection-4.2.35.dist-info/WHEEL
scriptcollection-4.2.35.dist-info/entry_points.txt
scriptcollection-4.2.35.dist-info/top_level.txt
scriptcollection-4.2.35.dist-info/RECORD
