Metadata-Version: 2.4
Name: ScriptCollection
Version: 4.2.35
Summary: The ScriptCollection is the place for reusable scripts.
Home-page: https://github.com/anionDev/ScriptCollection
Author: Marius Göcke
Author-email: marius.goecke@gmail.com
Project-URL: Documentation, https://aniondev.github.io/ScriptCollectionReference/index.html
Project-URL: Changelog, https://github.com/anionDev/ScriptCollection/tree/main/Other/Resources/Changelog
Keywords: package release build management
Classifier: Intended Audience :: Developers
Classifier: Topic :: Software Development :: Libraries :: Python Modules
Classifier: Programming Language :: Python :: 3.10
Classifier: License :: OSI Approved :: GNU General Public License v3 (GPLv3)
Classifier: Operating System :: POSIX :: Linux
Classifier: Operating System :: Microsoft :: Windows :: Windows 10
Classifier: Topic :: System :: Logging
Classifier: Topic :: System :: Monitoring
Classifier: Topic :: System :: Archiving :: Packaging
Classifier: Topic :: System :: Systems Administration
Classifier: Topic :: Terminals
Classifier: Topic :: Utilities
Requires-Python: >=3.10
Requires-Dist: build>=1.4.0
Requires-Dist: coverage>=7.13.2
Requires-Dist: cyclonedx-bom>=7.1.0
Requires-Dist: defusedxml>=0.7.1
Requires-Dist: keyboard>=0.13.5
Requires-Dist: lcov-cobertura>=2.1.1
Requires-Dist: lxml>=6.0.1
Requires-Dist: ntplib>=0.4.0
Requires-Dist: Pillow>=11.3.0
Requires-Dist: psutil>=7.2.2
Requires-Dist: pycdlib>=1.14.0
Requires-Dist: Pygments>=2.19.2
Requires-Dist: pylint>=4.0.4
Requires-Dist: pyOpenSSL>=25.3.0
Requires-Dist: PyPDF>=6.6.2
Requires-Dist: pytest>=8.4.2
Requires-Dist: PyYAML>=6.0.3
Requires-Dist: qrcode>=8.2.0
Requires-Dist: send2trash>=1.8.3
Requires-Dist: twine>=6.2.0
Requires-Dist: xmlschema>=4.3.1
